wagtail_azure_cdn/__init__.py
wagtail_azure_cdn/backends.py
wagtail_azure_cdn/tests/__init__.py
wagtail_azure_cdn/tests/settings.py
wagtail_azure_cdn/tests/test_backends.py
wagtail_azure_cdn/tests/urls.py
wagtail_azure_cdn-0.3.dist-info/LICENSE
wagtail_azure_cdn-0.3.dist-info/METADATA
wagtail_azure_cdn-0.3.dist-info/WHEEL
wagtail_azure_cdn-0.3.dist-info/top_level.txt
wagtail_azure_cdn-0.3.dist-info/RECORD
