Metadata-Version: 2.1
Name: wagtail-azure-cdn
Version: 0.3
Summary: Use Azure CDN with Wagtail
Home-page: https://github.com/tm-kn/wagtail-azure-cdn/
Author: Tomasz Knapik
Author-email: hi@tmkn.org
License: MIT
Platform: UNKNOWN
Classifier: Development Status :: 3 - Alpha
Classifier: Environment :: Web Environment
Classifier: Intended Audience :: Developers
Classifier: License :: OSI Approved :: MIT License
Classifier: Operating System :: OS Independent
Classifier: Programming Language :: Python
Classifier: Programming Language :: Python :: 3
Classifier: Programming Language :: Python :: 3.6
Classifier: Programming Language :: Python :: 3.7
Classifier: Programming Language :: Python :: 3.8
Classifier: Framework :: Django
Classifier: Framework :: Django :: 2.0
Classifier: Framework :: Django :: 2.1
Classifier: Framework :: Django :: 2.2
Classifier: Framework :: Wagtail
Classifier: Topic :: Internet :: WWW/HTTP :: Site Management
Requires-Python: >=3.6
Requires-Dist: wagtail
Provides-Extra: cdn
Requires-Dist: azure-mgmt-cdn (<2,>=1) ; extra == 'cdn'
Provides-Extra: frontdoor
Requires-Dist: azure-mgmt-frontdoor (<2,>=1) ; extra == 'frontdoor'
Provides-Extra: testing
Requires-Dist: flake8 ; extra == 'testing'
Requires-Dist: black ; extra == 'testing'
Requires-Dist: isort ; extra == 'testing'
Requires-Dist: faker ; extra == 'testing'
